{
  "date": "1995-02-08",
  "panels": [
    {
      "panel": 1,
      "dialogue": [
        "Day three of telecommuting:",
        "I spend the morning",
        "throwing my pen in the",
        "air."
      ]
    },
    {
      "panel": 2,
      "dialogue": [
        "Poink"
      ]
    },
    {
      "panel": 3,
      "dialogue": [
        "The afternoon is spent",
        "in silent appreciation",
        "of how much better this",
        "is than being in the",
        "office.",
        "Ahh"
      ]
    }
  ]
}