{
  "date": "1990-04-09",
  "panels": [
    {
      "panel": 1,
      "dialogue": [
        "The first thing you Elbonians must understand about capitalism is the incentive system."
      ]
    },
    {
      "panel": 2,
      "dialogue": [
        "If you're willing to work twelve hours a day, eventually the guy who owns your factory will get rich."
      ]
    },
    {
      "panel": 3,
      "dialogue": [
        "Am I missing something here?",
        "Then you guys get to watch great TV shows based on the millionaire's life!"
      ]
    }
  ]
}