{
  "date": "2013-04-05",
  "panels": [
    {
      "panel": 1,
      "dialogue": [
        "You designed our hardware with black buttons on a black case."
      ]
    },
    {
      "panel": 2,
      "dialogue": [
        "The user interface will be invisible in normal light.",
        "But more important, it looks great!"
      ]
    },
    {
      "panel": 3,
      "dialogue": [
        "You don't know what \"important\" means, do you?",
        "It sounds nerdy. I majored in art."
      ]
    }
  ]
}