{
  "date": "2009-02-10",
  "panels": [
    {
      "panel": 1,
      "dialogue": [
        "Dilbert works in collections",
        "My wife left me, my truck caught on fire, and all of my organs are failing."
      ]
    },
    {
      "panel": 2,
      "dialogue": [
        "I work in a collections department.",
        "You win."
      ]
    },
    {
      "panel": 3,
      "dialogue": [
        "Winning isn't what it used to be.",
        "Your five-minute break is over!"
      ]
    }
  ]
}