{
  "date": "1996-06-24",
  "panels": [
    {
      "panel": 1,
      "dialogue": [
        "Here's a draft of my new objectives.",
        "I tried to make them achievable."
      ]
    },
    {
      "panel": 2,
      "dialogue": [
        "No matter how stupid my co-workers are, I will not punch a hole in anyone's torso, rip out a vital organ and keep it in my cubicle as a warning to others."
      ]
    },
    {
      "panel": 3,
      "dialogue": [
        "I hope she gets those objectives approved.",
        "Yes! It's measurable!"
      ]
    }
  ]
}