{
  "date": "2004-07-19",
  "panels": [
    {
      "panel": 1,
      "dialogue": [
        "Catbert: Evil director of human resources",
        "Stock options will be replaced with a bonus system."
      ]
    },
    {
      "panel": 2,
      "dialogue": [
        "So...now my happiness depends on the kindness of management instead of the gullibility of our investors?"
      ]
    },
    {
      "panel": 3,
      "dialogue": [
        "Allow me to respond by hacking a hair-ball in your direction."
      ]
    }
  ]
}