{
  "date": "2006-12-12",
  "panels": [
    {
      "panel": 1,
      "dialogue": [
        "Flashback: Indian institute of technology.",
        "Your telekinesis grades are very good, young Asok."
      ]
    },
    {
      "panel": 2,
      "dialogue": [
        "Always remember that you may not use your powers in front of the ungifted."
      ]
    },
    {
      "panel": 3,
      "dialogue": [
        "Present day",
        "What the...? I just blinked and the last doughnut disappeared!"
      ]
    }
  ]
}